MANIFEST.in
README.rst
requirements.txt
setup.cfg
setup.py
bin/subile
subile/__init__.py
subile/__main__.py
subile/subtitles.py
subile/utils.py
subile.egg-info/PKG-INFO
subile.egg-info/SOURCES.txt
subile.egg-info/dependency_links.txt
subile.egg-info/requires.txt
subile.egg-info/top_level.txt