Metadata-Version: 1.1
Name: subile
Version: 0.0.1
Summary: Download subtitles in multiple languages from the terminal
Home-page: https://github.com/marcwebbie/subile
Author: Marcwebbie
Author-email: marcwebbie@gmail.com
License: MIT
Keywords: subtitles video caption media watch show film documentary
Platform: UNKNOWN
Classifier: Development Status :: 3 - Alpha
Classifier: Environment :: Console
Classifier: Intended Audience :: End Users/Desktop
Classifier: Natural Language :: English
Classifier: Operating System :: OS Independent
Classifier: Programming Language :: Python
Classifier: Programming Language :: Python :: 2.7
Classifier: Topic :: Multimedia :: Video
Classifier: Topic :: Internet
